[
    {
        "key": "sb",
        "value": "VrJ4aeq5O80StJUW5RtcoAUp",
        "domain": "facebook.com",
        "path": "/",
        "hostOnly": false,
        "creation": "2026-02-05T19:48:36.606Z",
        "lastAccessed": "2026-02-05T19:48:36.606Z"
    },
    {
        "key": "ps_l",
        "value": "1",
        "domain": "facebook.com",
        "path": "/",
        "hostOnly": false,
        "creation": "2026-02-05T19:48:36.606Z",
        "lastAccessed": "2026-02-05T19:48:36.606Z"
    },
    {
        "key": "ps_n",
        "value": "1",
        "domain": "facebook.com",
        "path": "/",
        "hostOnly": false,
        "creation": "2026-02-05T19:48:36.606Z",
        "lastAccessed": "2026-02-05T19:48:36.606Z"
    },
    {
        "key": "vpd",
        "value": "v1%3B656x360x2",
        "domain": "facebook.com",
        "path": "/",
        "hostOnly": false,
        "creation": "2026-02-05T19:48:36.606Z",
        "lastAccessed": "2026-02-05T19:48:36.606Z"
    },
    {
        "key": "datr",
        "value": "OHx-aReXyTxX0a5orLWzR-uN",
        "domain": "facebook.com",
        "path": "/",
        "hostOnly": false,
        "creation": "2026-02-05T19:48:36.606Z",
        "lastAccessed": "2026-02-05T19:48:36.606Z"
    },
    {
        "key": "locale",
        "value": "en_US",
        "domain": "facebook.com",
        "path": "/",
        "hostOnly": false,
        "creation": "2026-02-05T19:48:36.607Z",
        "lastAccessed": "2026-02-05T19:48:36.607Z"
    },
    {
        "key": "pas",
        "value": "100091454654358%3AfhMKN43BLN%2C61571736506794%3AxEfhwCkOZw%2C61583030037285%3AzeIoTj9Qd7%2C100091945146753%3AWELhQQXtnD",
        "domain": "facebook.com",
        "path": "/",
        "hostOnly": false,
        "creation": "2026-02-05T19:48:36.607Z",
        "lastAccessed": "2026-02-05T19:48:36.607Z"
    },
    {
        "key": "c_user",
        "value": "100091945146753",
        "domain": "facebook.com",
        "path": "/",
        "hostOnly": false,
        "creation": "2026-02-05T19:48:36.607Z",
        "lastAccessed": "2026-02-05T19:48:36.607Z"
    },
    {
        "key": "xs",
        "value": "1%3AK-kDVSBOtW68ug%3A2%3A1770313355%3A-1%3A-1",
        "domain": "facebook.com",
        "path": "/",
        "hostOnly": false,
        "creation": "2026-02-05T19:48:36.607Z",
        "lastAccessed": "2026-02-05T19:48:36.607Z"
    },
    {
        "key": "fr",
        "value": "0DVXfb4qBaCTGPsaq.AWd-3Xxp2tFB3r0X6wx5_7-uD_oQr5ktG4WXbht4YicTZWSLlMQ.BpeLJW..AAA.0.0.BphPQK.AWdAsEIFIkfL6Shc-wof9jMAZnk",
        "domain": "facebook.com",
        "path": "/",
        "hostOnly": false,
        "creation": "2026-02-05T19:48:36.607Z",
        "lastAccessed": "2026-02-05T19:48:36.607Z"
    },
    {
        "key": "fbl_st",
        "value": "101225431%3BT%3A29505348",
        "domain": "facebook.com",
        "path": "/",
        "hostOnly": false,
        "creation": "2026-02-05T19:48:36.607Z",
        "lastAccessed": "2026-02-05T19:48:36.607Z"
    },
    {
        "key": "wl_cbv",
        "value": "v2%3Bclient_version%3A3070%3Btimestamp%3A1770320907",
        "domain": "facebook.com",
        "path": "/",
        "hostOnly": false,
        "creation": "2026-02-05T19:48:36.607Z",
        "lastAccessed": "2026-02-05T19:48:36.607Z"
    }
]
